sparkai/__init__.py
sparkai/constants.py
sparkai/conversation/__init__.py
sparkai/core/__init__.py
sparkai/core/_api/__init__.py
sparkai/core/_api/beta_decorator.py
sparkai/core/_api/deprecation.py
sparkai/core/_api/internal.py
sparkai/core/_api/path.py
sparkai/core/_base_api.py
sparkai/core/caches.py
sparkai/core/callbacks/__init__.py
sparkai/core/callbacks/base.py
sparkai/core/callbacks/manager.py
sparkai/core/callbacks/stdout.py
sparkai/core/callbacks/streaming_stdout.py
sparkai/core/globals/__init__.py
sparkai/core/language_models/__init__.py
sparkai/core/language_models/base.py
sparkai/core/language_models/chat_models.py
sparkai/core/language_models/llms.py
sparkai/core/load/__init__.py
sparkai/core/load/dump.py
sparkai/core/load/load.py
sparkai/core/load/mapping.py
sparkai/core/load/serializable.py
sparkai/core/messages/__init__.py
sparkai/core/messages/ai.py
sparkai/core/messages/base.py
sparkai/core/messages/chat.py
sparkai/core/messages/function.py
sparkai/core/messages/human.py
sparkai/core/messages/image_chat.py
sparkai/core/messages/system.py
sparkai/core/messages/tool.py
sparkai/core/outputs/__init__.py
sparkai/core/outputs/chat_generation.py
sparkai/core/outputs/chat_result.py
sparkai/core/outputs/generation.py
sparkai/core/outputs/llm_result.py
sparkai/core/outputs/run_info.py
sparkai/core/prompt_values.py
sparkai/core/prompts/__init__.py
sparkai/core/prompts/base.py
sparkai/core/prompts/chat.py
sparkai/core/prompts/few_shot.py
sparkai/core/prompts/few_shot_with_templates.py
sparkai/core/prompts/image.py
sparkai/core/prompts/loading.py
sparkai/core/prompts/pipeline.py
sparkai/core/prompts/prompt.py
sparkai/core/prompts/string.py
sparkai/core/pydantic_v1/__init__.py
sparkai/core/pydantic_v1/dataclasses.py
sparkai/core/pydantic_v1/main.py
sparkai/core/runnables/__init__.py
sparkai/core/runnables/base.py
sparkai/core/runnables/branch.py
sparkai/core/runnables/config.py
sparkai/core/runnables/configurable.py
sparkai/core/runnables/fallbacks.py
spark_ai_python-0.4.4.dist-info/LICENSE
spark_ai_python-0.4.4.dist-info/METADATA
spark_ai_python-0.4.4.dist-info/WHEEL
spark_ai_python-0.4.4.dist-info/RECORD
