Metadata-Version: 2.1
Name: spark-ai-python
Version: 0.4.4
Summary: a sdk for iflytek's spark LLM.
License: MIT
Author: whybeyoung
Author-email: ybyang7@iflytek.com
Requires-Python: >=3.8.1,<3.13
Classifier: License :: OSI Approved :: MIT License
Classifier: Programming Language :: Python :: 3
Classifier: Programming Language :: Python :: 3.9
Classifier: Programming Language :: Python :: 3.10
Classifier: Programming Language :: Python :: 3.11
Provides-Extra: autogen
Provides-Extra: llama-index
Provides-Extra: proxy
Requires-Dist: aiohttp (>3.3)
Requires-Dist: fastapi[all] (>=0.110.0,<0.111.0) ; extra == "proxy"
Requires-Dist: httpx
Requires-Dist: jsonpatch
Requires-Dist: llama-index (>=0.10.24,<0.11.0)
Requires-Dist: llama-index-core (>=0.10.24.post1,<0.11.0) ; extra == "llama-index"
Requires-Dist: llama-index-vector-stores-chroma (>=0.1.6,<0.2.0)
Requires-Dist: nest-asyncio (>=1.6.0,<2.0.0)
Requires-Dist: nest_asyncio
Requires-Dist: packaging
Requires-Dist: pyautogen (>=0.2.20) ; extra == "autogen"
Requires-Dist: pydantic
Requires-Dist: python-dotenv
Requires-Dist: pyyaml
Requires-Dist: requests
Requires-Dist: tenacity
Requires-Dist: uvicorn (>=0.26.0) ; extra == "proxy"
Requires-Dist: websocket-client (>=1.7.0,<2.0.0)
Requires-Dist: websockets
